{
	"type": "it.polimi.se2019.model.Weapon",
    "cardColour": {
        "colour": "BLUE"
    },
    "price": [],
    "weaponEffects": [
    {
        "name": "basicMode",
        "priority": 3,
        "invalidEffects": [],
        "price":[],
        "maxHeight":1,
        "effectType":-1,
            "effects":[
                {
                    "priority": 3,
                    "targetSpecification": {
                        "tile": true,
                        "different": {
                            "first": false,
                            "second": []
                        },
						"previous":{
							"first": false,
							"second": []
						},
                        "radiusBetween": {
                            "first": -2,
                            "second": -2
                        },
                        "visible": 1,
                        "enlarge": 0
                    },
                    "actions": [
                        {
                            "actionType": "DAMAGE",
                            "value": 1,
                            "area": false
                        }
                    ],
                    "endable": false,
                    "name": "B1",
                    "invalidEffects": []
                },
                {
                    "priority": 3,
                    "targetSpecification": {
                        "tile": true,
                        "different": {
                            "first": false,
                            "second": []
                        },
						"previous":{
							"first": false,
							"second": []
						},
                        "radiusBetween": {
                            "first": -2,
                            "second": -2
                        },
                        "visible": 1,
                        "enlarge": 1
                    },
                    "actions": [
                        {
                            "actionType": "MOVE",
                            "value": 1,
                            "area": false
                        },
                        {
                            "actionType": "DAMAGE",
                            "value": 1,
                            "area": false
                        }
                    ],
                    "endable": false,
                    "name": "B2",
                    "invalidEffects": []
                },
                {
                    "priority": 3,
                    "targetSpecification": {
                        "tile": true,
                        "different": {
                            "first": false,
                            "second": []
                        },
						"previous":{
							"first": false,
							"second": []
						},
                        "radiusBetween": {
                            "first": -2,
                            "second": -2
                        },
                        "visible": 1,
                        "enlarge": 2
                    },
                    "actions": [
                        {
                            "actionType": "MOVE",
                            "value": 2,
                            "area": false
                        },
                        {
                            "actionType": "DAMAGE",
                            "value": 1,
                            "area": false
                        }
                    ],
                    "endable": false,
                    "name": "B3",
                    "invalidEffects": []
                }
            ]
        },
        {
            "name": "inPunisherMode",
            "priority": 3,
            "invalidEffects": [],
            "price": [
                {
                    "color": "RED"
                },
                {
                    "color": "YELLOW"
                }
            ],
            "maxHeight":1,
            "effectType":0,
            "effects": [
                 {
                    "priority": 3,
                    "targetSpecification": {
                        "tile": true,
                        "different": {
                            "first": false,
                            "second": []
                        },
						"previous":{
							"first": false,
							"second": []
						},
                        "radiusBetween": {
                            "first": -2,
                            "second": -2
                        },
                        "visible": 1,
                        "enlarge": 0
                    },
                    "actions": [
                        {
                            "actionType": "DAMAGE",
                            "value": 3,
                            "area": false
                        }
                    ],
                     "endable": false,
                    "name": "B4",
                     "invalidEffects": []
                },
                {
                    "priority": 3,
                    "targetSpecification": {
                        "tile": true,
                        "different": {
                            "first": false,
                            "second": []
                        },
						"previous":{
							"first": false,
							"second": []
						},
                        "radiusBetween": {
                            "first": -2,
                            "second": -2
                        },
                        "visible": 1,
                        "enlarge": 1
                    },
                    "actions": [
                        {
                            "actionType": "MOVE",
                            "value": 1,
                            "area": false
                        },
                        {
                            "actionType": "DAMAGE",
                            "value": 3,
                            "area": false
                        }
                    ],
                    "endable": false,
                    "name": "B5",
                    "invalidEffects": []
                },
                {
                    "priority": 3,
                    "targetSpecification": {
                        "tile": true,
                        "different": {
                            "first": false,
                            "second": []
                        },
						"previous":{
							"first": false,
							"second": []
						},
                        "radiusBetween": {
                            "first": -2,
                            "second": -2
                        },
                        "visible": 1,
                        "enlarge": 2
                    },
                    "actions": [
                        {
                            "actionType": "MOVE",
                            "value": 2,
                            "area": false
                        },
                        {
                            "actionType": "DAMAGE",
                            "value": 3,
                            "area": false
                        }
                    ],
                    "endable": false,
                    "name": "B6",
                    "invalidEffects": []
                }
            ]
        }
    ],
    "name": "TractorBeam",
    "maxHeight": 1,
    "constraint": ""
}
